LICENSE.txt
MANIFEST.in
README.md
requirements.txt
setup.py
nodepy/__init__.py
nodepy/base.py
nodepy/context.py
nodepy/extensions.py
nodepy/loader.py
nodepy/main.py
nodepy/resolver.py
nodepy/runtime.py
nodepy/utils/__init__.py
nodepy/utils/config.py
nodepy/utils/context.py
nodepy/utils/iter.py
nodepy/utils/json.py
nodepy/utils/machinery.py
nodepy/utils/tracing.py
nodepy/utils/path/__init__.py
nodepy/utils/path/_core.py
nodepy/utils/path/urlpath.py
nodepy/utils/path/voidpath.py
nodepy/utils/path/zippath.py
nodepy_runtime.egg-info/PKG-INFO
nodepy_runtime.egg-info/SOURCES.txt
nodepy_runtime.egg-info/dependency_links.txt
nodepy_runtime.egg-info/entry_points.txt
nodepy_runtime.egg-info/requires.txt
nodepy_runtime.egg-info/top_level.txt