Metadata-Version: 2.1
Name: nodepy-runtime
Version: 2.1.3
Summary: Python with a Node.js-like module system.
Home-page: https://github.com/nodepy/nodepy
Author: Niklas Rosenstein
Author-email: rosensteinniklas@gmail.com
License: MIT
Platform: UNKNOWN
